llama_index/readers/mbox/__init__.py
llama_index/readers/mbox/base.py
llama_index_readers_mbox-0.5.1.dist-info/METADATA
llama_index_readers_mbox-0.5.1.dist-info/WHEEL
llama_index_readers_mbox-0.5.1.dist-info/licenses/LICENSE
llama_index_readers_mbox-0.5.1.dist-info/RECORD
